{
  "version": 1,
  "updated_on": "2026-03-03",
  "requests": [
    {
      "request_id": "REQ-2026-001",
      "account_id": "contoso-financial-services",
      "requestor_role": "Renewals Manager",
      "topic": "CI",
      "stage": "renew",
      "desired_outcome": "Raise CI reliability evidence before renewal committee review",
      "definition_of_done": "CI score > 60 and approved reliability summary shared in EBR deck",
      "due_date": "2026-03-08",
      "status": "new",
      "assigned_to": "Unassigned",
      "created_on": "2026-03-02"
    },
    {
      "request_id": "REQ-2026-002",
      "account_id": "northwind-industries",
      "requestor_role": "Account Executive",
      "topic": "Secure",
      "stage": "enable",
      "desired_outcome": "Increase secure baseline adoption for regulated repos",
      "definition_of_done": "At least 40% of regulated repos running SAST and dependency scanning",
      "due_date": "2026-03-12",
      "status": "in_progress",
      "assigned_to": "CSE Pool - Secure",
      "created_on": "2026-03-01"
    },
    {
      "request_id": "REQ-2026-003",
      "account_id": "adatum-energy",
      "requestor_role": "Account Executive",
      "topic": "CD",
      "stage": "optimize",
      "desired_outcome": "Improve deployment consistency with release automation",
      "definition_of_done": "Rollback rate below 8% and deployment runbook adopted by release team",
      "due_date": "2026-03-18",
      "status": "triage",
      "assigned_to": "CSE Pool - Release",
      "created_on": "2026-02-28"
    },
    {
      "request_id": "REQ-2026-004",
      "account_id": "fabrikam-retail-group",
      "requestor_role": "Renewals Manager",
      "topic": "Secure",
      "stage": "expand",
      "desired_outcome": "Prepare expansion narrative for two product lines",
      "definition_of_done": "Secure value summary approved by customer sponsor",
      "due_date": "2026-03-22",
      "status": "completed",
      "assigned_to": "CSE Pool - Secure",
      "created_on": "2026-02-20"
    }
  ]
}